README.md
setup.cfg
setup.py
tag_replicate.py
tag_replicator.egg-info/PKG-INFO
tag_replicator.egg-info/SOURCES.txt
tag_replicator.egg-info/dependency_links.txt
tag_replicator.egg-info/entry_points.txt
tag_replicator.egg-info/requires.txt
tag_replicator.egg-info/top_level.txt
taggers/__init__.py
taggers/backup.py
taggers/ec2.py
taggers/efs.py
taggers/eks.py
taggers/elb.py
taggers/lambda_fn.py
taggers/logs.py
taggers/rds.py
taggers/s3.py
taggers/sns_sqs.py
tests/test_tag_replicate.py