Metadata-Version: 2.4
Name: tag-replicator
Version: 0.1
Summary: AWS Tag Replicator CLI
Author: Nelson Almeida
Requires-Dist: boto3
Dynamic: requires-dist
